{"events":[{"date":"30/01/2015","time":"20.00","place":"Borda Brasil ","summary":"Samba Esporte Fino","promotion":"Pizza média por R$ 20,00 *"},
{"date":"31/01/2015","time":"21.30","place":"Casa São Jorge","summary":"Exposição \"A cena por aí\" de Arthur Amaral","promotion":"Entrada R$15,00 *"},
{"date":"01/02/2015","time":"21.30","place":"Echos Studio Bar","summary":"Quinteto Neblina e Paula D' Ajello","promotion":"Entrada Livre *"},
{"date":"02/02/2015","time":"21.30","place":"Andanças Gourmet, Bar e Restaurante","summary":"","promotion":"Ganha um chope (promoção facebook) *"},
{"date":"03/02/2015","time":"22.00","place":"Bagdá Cozinha Árabe","summary":"João Arruda","promotion":"5% de desconto na conta *"},
{"date":"04/02/2015","time":"22.00","place":"Almanaque Café","summary":"Cabaret de Variedades","promotion":"Ganha um chope *"},
{"date":"05/02/2015","time":"21.30","place":"Canto do Acarajé","summary":"Roda de Samba","promotion":"5% de desconto na conta *"},
{"date":"06/02/2015","time":"21.30","place":"Chopp do Fritz","summary":"","promotion":"50% de desconto nas refeições *"},
{"date":"07/02/2015","time":"21.30","place":"Chica da Pizza","summary":"Quarteto Seu Zé","promotion":""},
{"date":"08/02/2015","time":"21.30","place":"Centro Cultural Casarão ","summary":"Com comidinhas do Bagdá Cozinha Árabe","promotion":""},
{"date":"09/02/2015","time":"21.30","place":"Andanças Gourmet, Bar e Restaurante","summary":"Flautins de Matuá","promotion":"Ganha um chope (promoção facebook) *"},
{"date":"10/02/2015","time":"21.30","place":"Bar do Jair","summary":"Thiago Carvalho e Paulo Moraes","promotion":"Entrada R$ 5,00 *"},
{"date":"11/02/2015","time":"21.30","place":"Casa São Jorge","summary":"Tatiana Rocha","promotion":"Entrada R$ 7,00 *"},
{"date":"12/02/2015","time":"21.30","place":"Echos Studio Bar","summary":"Balé Barbárie","promotion":"Entrada: R$ 8,00 / na compra de 3 chopes só paga 2 *"},
           {"date":"13/02/2015","time":"18.00","place":"Praça do Coco","summary":"Festa de Encerramento com DJ Digão","promotion":""}]}

